code_searcher/__init__.py
code_searcher/additional_functions.py
code_searcher/code_searcher_class.py
code_searcher/working_with_files.py
code_searcher-0.2.1.dist-info/AUTHORS.rst
code_searcher-0.2.1.dist-info/LICENSE.txt
code_searcher-0.2.1.dist-info/METADATA
code_searcher-0.2.1.dist-info/WHEEL
code_searcher-0.2.1.dist-info/top_level.txt
code_searcher-0.2.1.dist-info/RECORD
